notedata/__init__.py
notedata/dataset/__init__.py
notedata/dataset/core.py
notedata/dataset/datas.py
notedata/dataset/images.py
notedata/manage/__init__.py
notedata/manage/core.py
notedata/manage/dataset.db
notedata/manage/library.py
notedata/paths/__init__.py
notedata/paths/core.py
notedata/tables_bak/__init__.py
notedata/tables_bak/core.py
notedata/work/__init__.py
notedata/work/core.py
notedata-0.8.22.dist-info/METADATA
notedata-0.8.22.dist-info/WHEEL
notedata-0.8.22.dist-info/top_level.txt
notedata-0.8.22.dist-info/RECORD
