Metadata-Version: 2.1
Name: notedata
Version: 0.8.22
Summary: notedata
Home-page: https://github.com/1007530194
Author: euler
Author-email: 1007530194@qq.com
License: UNKNOWN
Platform: UNKNOWN
Requires-Dist: notetool
Requires-Dist: notedrive
